edward/__init__.py
edward/version.py
edward/criticisms/__init__.py
edward/criticisms/evaluate.py
edward/criticisms/ppc.py
edward/criticisms/ppc_plots.py
edward/inferences/__init__.py
edward/inferences/bigan_inference.py
edward/inferences/gan_inference.py
edward/inferences/gibbs.py
edward/inferences/hmc.py
edward/inferences/implicit_klqp.py
edward/inferences/inference.py
edward/inferences/klpq.py
edward/inferences/klqp.py
edward/inferences/laplace.py
edward/inferences/map.py
edward/inferences/metropolis_hastings.py
edward/inferences/monte_carlo.py
edward/inferences/sghmc.py
edward/inferences/sgld.py
edward/inferences/variational_inference.py
edward/inferences/wake_sleep.py
edward/inferences/wgan_inference.py
edward/inferences/conjugacy/__init__.py
edward/inferences/conjugacy/conjugacy.py
edward/inferences/conjugacy/conjugate_log_probs.py
edward/inferences/conjugacy/simplify.py
edward/models/__init__.py
edward/models/dirichlet_process.py
edward/models/empirical.py
edward/models/param_mixture.py
edward/models/point_mass.py
edward/models/random_variable.py
edward/models/random_variables.py
edward/util/__init__.py
edward/util/graphs.py
edward/util/metrics.py
edward/util/progbar.py
edward/util/random_variables.py
edward/util/tensorflow.py
edward-1.3.5.dist-info/DESCRIPTION.rst
edward-1.3.5.dist-info/METADATA
edward-1.3.5.dist-info/RECORD
edward-1.3.5.dist-info/WHEEL
edward-1.3.5.dist-info/metadata.json
edward-1.3.5.dist-info/top_level.txt
