Metadata-Version: 2.0
Name: edward
Version: 1.3.5
Summary: A library for probabilistic modeling, inference, and criticism
Home-page: http://edwardlib.org
Author: Dustin Tran
Author-email: dustin@cs.columbia.edu
License: Apache License 2.0
Keywords: machine learning statistics probabilistic programming tensorflow
Platform: UNKNOWN
Classifier: Intended Audience :: Developers
Classifier: Intended Audience :: Education
Classifier: Intended Audience :: Science/Research
Classifier: License :: OSI Approved :: Apache Software License
Classifier: Operating System :: POSIX :: Linux
Classifier: Operating System :: MacOS :: MacOS X
Classifier: Operating System :: Microsoft :: Windows
Classifier: Programming Language :: Python :: 2.7
Classifier: Programming Language :: Python :: 3.4
Requires-Dist: numpy (>=1.7)
Requires-Dist: six (>=1.10.0)
Provides-Extra: datasets
Requires-Dist: observations (>=0.1.2); extra == 'datasets'
Provides-Extra: neural networks
Requires-Dist: keras (<=2.0.4,>=1.0.0); extra == 'neural networks'
Requires-Dist: prettytensor (>=0.7.4); extra == 'neural networks'
Provides-Extra: notebooks
Requires-Dist: jupyter (>=1.0.0); extra == 'notebooks'
Provides-Extra: tensorflow
Requires-Dist: tensorflow (>=1.2.0rc0); extra == 'tensorflow'
Provides-Extra: tensorflow with gpu
Requires-Dist: tensorflow-gpu (>=1.2.0rc0); extra == 'tensorflow with gpu'
Provides-Extra: visualization
Requires-Dist: matplotlib (>=1.3); extra == 'visualization'
Requires-Dist: pillow (>=3.4.2); extra == 'visualization'
Requires-Dist: seaborn (>=0.3.1); extra == 'visualization'
